streamlamp/__init__.py
streamlamp/snowflake/__init__.py
streamlamp/sqlite3/__init__.py
streamlamp-0.2.dist-info/METADATA
streamlamp-0.2.dist-info/WHEEL
streamlamp-0.2.dist-info/top_level.txt
streamlamp-0.2.dist-info/RECORD
