Metadata-Version: 2.1
Name: streamlamp
Version: 0.2
Summary: An adjunct library for serious Streamlit application development
Author: jhunt
Project-URL: Documentation, https://github.com/jhunt/streamlamp/blob/main/README.md
Project-URL: Issues, https://github.com/jhunt/streamlamp/issues
Project-URL: Source, https://github.com/jhunt/streamlamp
Classifier: Programming Language :: Python :: 3.9
Classifier: License :: OSI Approved :: MIT License
Classifier: Operating System :: OS Independent
Requires-Python: >=3.9
Requires-Dist: requests
